Metadata-Version: 1.0
Name: play-tictactoe
Version: 0.2
Summary: tic tac toe game for two
Home-page: UNKNOWN
Author: UNKNOWN
Author-email: UNKNOWN
License: UNKNOWN
Platform: UNKNOWN
